{
  "version": "0.1.0",
  "generated_at": "2026-06-28T18:05:06.060395800+00:00",
  "epsilon": 0.3,
  "epsilon_declaration": "本系统承认：即使所有参数都被精确测量，即使所有耦合关系都被理解，即使所有动态机制都被建模——仍然存在不可通约余数ε。ε不是误差，不是未发现的参数，不是模型的缺陷。ε是人格不能被还原为参数的根本原因。ε是本系统的自我否定——也是本系统最重要的部分。",
  "parameters": {
    "C028": {
      "name": "自主性需求",
      "domain": "动机与价值",
      "value": 0.9481222336030792,
      "definition": "被指令/控制时系统产生的阻抗力强度"
    },
    "B012": {
      "name": "情绪颗粒度",
      "domain": "情绪生成与调节",
      "value": 0.12302042727381157,
      "definition": "能够区分的离散情绪状态的数量和精度"
    },
    "B023": {
      "name": "嫉妒触发敏感度",
      "domain": "情绪生成与调节",
      "value": 0.9129043286216736,
      "definition": "他人优势(地位/能力/关系/物质)触发嫉妒情绪的最小差距阈值"
    },
    "F057": {
      "name": "自我暴露深度梯度",
      "domain": "社交信号",
      "value": 0.2156031202216564,
      "definition": "第N次见面时愿意暴露的个人信息深度"
    },
    "F058": {
      "name": "社交代价敏感度",
      "domain": "社交信号",
      "value": 0.14384085886024045,
      "definition": "系统在拒绝/反对他人前脑内模拟对方反应的强度和数量"
    },
    "B015": {
      "name": "内疚感基线",
      "domain": "情绪生成与调节",
      "value": 0.5570959069355466,
      "definition": "对自身行为造成他人痛苦后的内疚反应强度"
    },
    "B021": {
      "name": "情绪传染易感性",
      "domain": "情绪生成与调节",
      "value": 0.13680755397970223,
      "definition": "他人情绪表达触发自身相同情绪的自动化程度"
    },
    "D039": {
      "name": "行为蓄能时间",
      "domain": "行为执行",
      "value": 110.54133635777455,
      "definition": "从决定行动到实际开始行动之间的时间延迟"
    },
    "G065": {
      "name": "情境人格切换幅度",
      "domain": "时间性与发展",
      "value": 0.8794273216359985,
      "definition": "同一参数在不同情境(家庭/职场/独处/社交)间的取值差异幅度"
    },
    "G066": {
      "name": "身份叙事更新速率",
      "domain": "时间性与发展",
      "value": 324.3734754221863,
      "definition": "系统的自我定义在新经历后更新的速度"
    },
    "H076": {
      "name": "运动-情绪提升",
      "domain": "身体-环境耦合",
      "value": 0.37361311474615655,
      "definition": "身体运动对情绪状态的提升幅度"
    },
    "C030": {
      "name": "冲动控制缓冲",
      "domain": "动机与价值",
      "value": 0.9068398103913221,
      "definition": "冲动产生到行为执行之间的缓冲时间长度"
    },
    "H078": {
      "name": "噪音-压力耦联",
      "domain": "身体-环境耦合",
      "value": 0.5637459448216908,
      "definition": "环境噪音对压力水平的提升幅度"
    },
    "A009": {
      "name": "痛苦线索敏感度",
      "domain": "信息摄入",
      "value": 0.19316373869311998,
      "definition": "对他人痛苦表情/声音/姿态的注意捕获强度"
    },
    "A006": {
      "name": "背景-前景分离效率",
      "domain": "信息摄入",
      "value": 0.9349390665092505,
      "definition": "在多声源/多刺激环境中提取目标信息的速度"
    },
    "B016": {
      "name": "他人痛苦-自身愉悦转化",
      "domain": "情绪生成与调节",
      "value": 0.18293732744102265,
      "definition": "感知到他人痛苦时自身产生愉悦(正)或不适(负)的强度"
    },
    "A004": {
      "name": "社会性线索优先级",
      "domain": "信息摄入",
      "value": 0.4670784346150756,
      "definition": "面孔/注视方向/身体朝向相对于非社会性物体的注意优先级"
    },
    "F056": {
      "name": "面部镜像延迟",
      "domain": "社交信号",
      "value": 248.09738457399354,
      "definition": "对方表情出现后自身对应肌肉激活的时间延迟"
    },
    "H081": {
      "name": "饥饿-风险偏好",
      "domain": "身体-环境耦合",
      "value": 0.08675747167001635,
      "definition": "饥饿状态对风险决策的影响方向与强度"
    },
    "E053": {
      "name": "矛盾共存耐受",
      "domain": "元认知与自我",
      "value": 14.942253813844227,
      "definition": "系统同时持有冲突信念/情感而不产生焦虑的能力"
    },
    "A007": {
      "name": "预期违背消耗",
      "domain": "信息摄入",
      "value": 0.4474551720751341,
      "definition": "处理不符合预期的信息时消耗的认知资源比例"
    },
    "E044": {
      "name": "反刍思维强度",
      "domain": "元认知与自我",
      "value": 0.5945054257938005,
      "definition": "系统反复咀嚼负面经历的自动化程度"
    },
    "C034": {
      "name": "地位渴求",
      "domain": "动机与价值",
      "value": 0.28436422559314845,
      "definition": "需要感到自己比他人优越/受他人尊重的心理驱力强度"
    },
    "B013": {
      "name": "自动思维情绪附着力",
      "domain": "情绪生成与调节",
      "value": 0.9598070780421968,
      "definition": "一个自动产生的想法所携带的情绪冲击强度"
    },
    "C025": {
      "name": "趋近-回避基线",
      "domain": "动机与价值",
      "value": -0.41674058013095605,
      "definition": "面对中性/陌生刺激时系统的默认行为倾向"
    },
    "H084": {
      "name": "海拔-思维抽象度",
      "domain": "身体-环境耦合",
      "value": 0.055990769960877707,
      "definition": "物理高度对思维抽象程度的影响"
    },
    "E048": {
      "name": "道德推脱能力",
      "domain": "元认知与自我",
      "value": 0.662058733921236,
      "definition": "系统为自身不道德行为找到合理化理由的容易程度"
    },
    "E052": {
      "name": "道德-审美耦合度",
      "domain": "元认知与自我",
      "value": 0.707997930477946,
      "definition": "系统感知「善」与感知「美」在大脑中的重叠程度"
    },
    "B020": {
      "name": "情绪标签命名速度",
      "domain": "情绪生成与调节",
      "value": 0.4453457639428003,
      "definition": "从情绪产生到能用语言准确描述该情绪的时间延迟"
    },
    "A010": {
      "name": "猎物/捕食者注意偏向",
      "domain": "信息摄入",
      "value": -0.00805698199592797,
      "definition": "注意资源自动流向弱者(猎物)还是强者(捕食者)的倾向"
    },
    "C033": {
      "name": "亲和动机",
      "domain": "动机与价值",
      "value": 0.40808400860611793,
      "definition": "建立和维持温暖人际关系的驱力强度"
    },
    "C029": {
      "name": "胜任感锚点",
      "domain": "动机与价值",
      "value": 0.6329503205343483,
      "definition": "系统认为自己「够好」所需的最低客观证据数量"
    },
    "A003": {
      "name": "内感受分辨率",
      "domain": "信息摄入",
      "value": 0.5390389508964792,
      "definition": "对自身躯体信号(心跳、呼吸、胃紧、肌肉张力)的觉察精度"
    },
    "D040": {
      "name": "攻击行为基线",
      "domain": "行为执行",
      "value": 0.35028622394988185,
      "definition": "系统在无挑衅情况下发起攻击行为的概率"
    },
    "E047": {
      "name": "自我感知校准度",
      "domain": "元认知与自我",
      "value": 0.12678609682948272,
      "definition": "系统对自身能力/性格/道德的评价与客观测量的偏差程度"
    },
    "E054": {
      "name": "框架重构力",
      "domain": "元认知与自我",
      "value": 0.6137120036276709,
      "definition": "系统将事件从一种意义框架重新定义为另一种意义框架的能力"
    },
    "H079": {
      "name": "气味-记忆唤起率",
      "domain": "身体-环境耦合",
      "value": 0.8093921343421517,
      "definition": "气味触发自传体记忆的概率和强度"
    },
    "A008": {
      "name": "威胁线索放大系数",
      "domain": "信息摄入",
      "value": 0.7128811485677105,
      "definition": "将模糊/中性刺激解读为威胁信号的倾向强度"
    },
    "A002": {
      "name": "听觉歧义容忍窗口",
      "domain": "信息摄入",
      "value": 4.710036417289551,
      "definition": "对模糊语音/语调保持多解而不急于消歧的持续时间"
    },
    "E055": {
      "name": "自我欺骗强度",
      "domain": "元认知与自我",
      "value": 0.1773073746349858,
      "definition": "系统相信自己明知为假的自我叙述的程度"
    },
    "B019": {
      "name": "愤怒-攻击转化率",
      "domain": "情绪生成与调节",
      "value": 0.10770730741982582,
      "definition": "愤怒情绪直接转化为攻击行为(言语或身体)的概率"
    },
    "F059": {
      "name": "欺骗生理舒适度",
      "domain": "社交信号",
      "value": 0.719120673941487,
      "definition": "系统说谎时自主神经系统的激活程度(反向：越舒适=越不激活)"
    },
    "B024": {
      "name": "幸灾乐祸阈限",
      "domain": "情绪生成与调节",
      "value": 0.3112284656834863,
      "definition": "他人不幸触发愉悦反应的最小不幸程度"
    },
    "H072": {
      "name": "昼夜节律-创造力",
      "domain": "身体-环境耦合",
      "value": 0.40807534793633726,
      "definition": "昼夜节律阶段对创造性思维的影响幅度"
    },
    "C037": {
      "name": "价值-行为一致性",
      "domain": "动机与价值",
      "value": 0.9133535511268009,
      "definition": "系统声称的价值观与实际行为之间的相关程度"
    },
    "C038": {
      "name": "刺激寻求",
      "domain": "动机与价值",
      "value": 0.8842713857078162,
      "definition": "为获得快感/兴奋而追求新奇/危险/禁忌体验的驱力强度"
    },
    "E050": {
      "name": "自我批评强度",
      "domain": "元认知与自我",
      "value": 0.07241683151488987,
      "definition": "系统对自身错误/缺陷产生自我批评的强度"
    },
    "H073": {
      "name": "微表情抑制力",
      "domain": "身体-环境耦合",
      "value": 0.6943474514306676,
      "definition": "抑制面部微表情泄露真实情绪的能力"
    },
    "H083": {
      "name": "温度-攻击性",
      "domain": "身体-环境耦合",
      "value": 0.7874702989263549,
      "definition": "环境温度对攻击行为的影响强度"
    },
    "E043": {
      "name": "思维标签化频率",
      "domain": "元认知与自我",
      "value": 0.5288461299201961,
      "definition": "系统能够将自身思维过程作为观察对象的频率"
    },
    "A001": {
      "name": "视觉采样率",
      "domain": "信息摄入",
      "value": 4.254102918860015,
      "definition": "单位时间内视觉注意点的切换频率"
    },
    "B022": {
      "name": "怨恨衰减半衰期",
      "domain": "情绪生成与调节",
      "value": 58.67287802921753,
      "definition": "被冒犯/伤害后怨恨情绪的强度衰减到原始强度一半所需的时间"
    },
    "C032": {
      "name": "权力动机",
      "domain": "动机与价值",
      "value": 0.8520533896664606,
      "definition": "渴望影响/控制他人或环境的驱力强度"
    },
    "D041": {
      "name": "规则遵循度",
      "domain": "行为执行",
      "value": 0.522841797268341,
      "definition": "系统遵守外部规则(法律/规范/命令)的默认程度"
    },
    "E045": {
      "name": "内隐自尊",
      "domain": "元认知与自我",
      "value": 0.8583914184767831,
      "definition": "系统在潜意识层面对自己的积极/消极评价"
    },
    "E051": {
      "name": "使命感清晰度",
      "domain": "元认知与自我",
      "value": 0.45592439488104275,
      "definition": "系统对「我为何而活」有明确答案的程度"
    },
    "A005": {
      "name": "新异刺激打断阈值",
      "domain": "信息摄入",
      "value": 0.7320883674851029,
      "definition": "意外刺激使当前注意焦点发生偏移的最小强度"
    },
    "H074": {
      "name": "疼痛-攻击链接",
      "domain": "身体-环境耦合",
      "value": 0.09917652679701594,
      "definition": "身体疼痛转化为攻击冲动的强度"
    },
    "C027": {
      "name": "延迟折扣率",
      "domain": "动机与价值",
      "value": 0.7997600990096976,
      "definition": "未来奖赏在当下主观价值中的折扣程度"
    },
    "H075": {
      "name": "光照-决策速度",
      "domain": "身体-环境耦合",
      "value": 0.13791317841753048,
      "definition": "环境光照强度对决策速度的影响"
    },
    "H077": {
      "name": "睡眠债务-认知衰减",
      "domain": "身体-环境耦合",
      "value": 0.7161264163931547,
      "definition": "睡眠不足对认知功能的衰减速率"
    },
    "B011": {
      "name": "基础情绪唤醒阈值",
      "domain": "情绪生成与调节",
      "value": 0.544782373963663,
      "definition": "愤怒/恐惧/悲伤/喜悦四种基本情绪各自被激活的最小刺激强度"
    },
    "H070": {
      "name": "温度-社交距离",
      "domain": "身体-环境耦合",
      "value": 0.6504710331699466,
      "definition": "环境温度对社交距离偏好的影响强度"
    },
    "C031": {
      "name": "支配-顺从倾向",
      "domain": "动机与价值",
      "value": 0.6109655599154169,
      "definition": "在人际等级中系统默认追求的位置"
    },
    "H080": {
      "name": "触觉-信任关联",
      "domain": "身体-环境耦合",
      "value": 0.3662266147292723,
      "definition": "身体接触对信任建立的影响强度"
    },
    "C026": {
      "name": "意义寻求强度",
      "domain": "动机与价值",
      "value": 15.066928641531703,
      "definition": "系统自动追问「这有什么意义」的频率和深度"
    },
    "E046": {
      "name": "外显自尊",
      "domain": "元认知与自我",
      "value": 0.6163450887931161,
      "definition": "系统在意识层面声称的自我价值感"
    },
    "H068": {
      "name": "呼吸-情绪耦联",
      "domain": "身体-环境耦合",
      "value": 0.5213559569317352,
      "definition": "呼吸模式与情绪状态的互锁强度"
    },
    "B017": {
      "name": "羞耻感基线",
      "domain": "情绪生成与调节",
      "value": 0.27792064044090026,
      "definition": "在公开场合暴露缺陷/违规/失误后产生的羞耻反应强度"
    },
    "H067": {
      "name": "坐姿-思维关联",
      "domain": "身体-环境耦合",
      "value": 0.9004941288830364,
      "definition": "身体姿态对思维模式的影响强度"
    },
    "E049": {
      "name": "责任归因偏向",
      "domain": "元认知与自我",
      "value": -0.4432741266802971,
      "definition": "系统将事件原因归因于自身(-1)还是外部(+1)的默认偏向"
    },
    "F062": {
      "name": "背叛检测灵敏度",
      "domain": "社交信号",
      "value": 0.0692441569434088,
      "definition": "系统识别欺骗/利用/背叛线索的警觉程度"
    },
    "H071": {
      "name": "饱腹-慷慨",
      "domain": "身体-环境耦合",
      "value": 0.04545561904375317,
      "definition": "饥饿/饱腹状态对慷慨行为的影响强度"
    },
    "H069": {
      "name": "手势-语速锁定",
      "domain": "身体-环境耦合",
      "value": 0.358621946299279,
      "definition": "手势与言语节奏的同步程度"
    },
    "C035": {
      "name": "利他惩罚倾向",
      "domain": "动机与价值",
      "value": 0.3404423225204225,
      "definition": "愿意自掏成本惩罚不公平/违规行为的强度"
    },
    "H082": {
      "name": "姿势-权力感映射",
      "domain": "身体-环境耦合",
      "value": 0.48450759602059557,
      "definition": "身体姿势(扩张/收缩)对权力感的影响强度"
    },
    "B018": {
      "name": "积极情绪维持能力",
      "domain": "情绪生成与调节",
      "value": 0.9824404233124056,
      "definition": "积极情绪(喜悦/满足/宁静)产生后持续的时间长度"
    },
    "G063": {
      "name": "参数漂移速率",
      "domain": "时间性与发展",
      "value": 0.24853267501019172,
      "definition": "各参数随时间定向变化的速度(每个参数独立)"
    },
    "D042": {
      "name": "行为灵活性",
      "domain": "行为执行",
      "value": 0.8500340432098961,
      "definition": "原计划受阻时切换到替代方案的速度"
    },
    "F061": {
      "name": "信任默认值",
      "domain": "社交信号",
      "value": 0.016850382982900536,
      "definition": "系统在未经验证前对陌生人的初始信任水平"
    },
    "C036": {
      "name": "欺骗接受度",
      "domain": "动机与价值",
      "value": 0.5360874032545209,
      "definition": "系统将欺骗视为合理行为手段的程度"
    },
    "G064": {
      "name": "重大事件相变阈值",
      "domain": "时间性与发展",
      "value": 0.8111581476576863,
      "definition": "引起参数永久偏移所需的最小事件冲击强度"
    },
    "B014": {
      "name": "情绪调节策略库",
      "domain": "情绪生成与调节",
      "value": 1.96858071796628,
      "definition": "系统可主动调用的情绪调节方法的数量和有效性"
    },
    "F060": {
      "name": "印象管理精细度",
      "domain": "社交信号",
      "value": 0.024455831953137608,
      "definition": "系统刻意控制他人对自己印象的策略复杂程度"
    }
  },
  "inactive_parameters": [],
  "couplings": [
    {
      "param_a": "E045",
      "param_b": "E046",
      "phenomenon": "低内隐+高外显=表面自信内心自卑(脆弱型)",
      "value_a": 0.8583914184767831,
      "value_b": 0.6163450887931161
    },
    {
      "param_a": "E045",
      "param_b": "C031",
      "phenomenon": "低内隐+高支配=用控制他人逃避自我厌恶",
      "value_a": 0.8583914184767831,
      "value_b": 0.6109655599154169
    },
    {
      "param_a": "B023",
      "param_b": "A009",
      "phenomenon": "嫉妒某人且无视其痛苦(毁灭型嫉妒)",
      "value_a": 0.9129043286216736,
      "value_b": 0.19316373869311998
    },
    {
      "param_a": "B013",
      "param_b": "B018",
      "phenomenon": "一个积极想法触发持续的积极情绪",
      "value_a": 0.9598070780421968,
      "value_b": 0.9824404233124056
    },
    {
      "param_a": "C038",
      "param_b": "C030",
      "phenomenon": "高刺激寻求+低冲动控制=高风险行为型",
      "value_a": 0.8842713857078162,
      "value_b": 0.9068398103913221
    },
    {
      "param_a": "G066",
      "param_b": "G064",
      "phenomenon": "固定自我+高相变阈值=「我一直都是这样的人」",
      "value_a": 324.3734754221863,
      "value_b": 0.8111581476576863
    },
    {
      "param_a": "A001",
      "param_b": "A009",
      "phenomenon": "看到一切但看不到人",
      "value_a": 4.254102918860015,
      "value_b": 0.19316373869311998
    },
    {
      "param_a": "B022",
      "param_b": "B019",
      "phenomenon": "内心燃烧但表面平静(冷怨恨/冷暴力)",
      "value_a": 58.67287802921753,
      "value_b": 0.10770730741982582
    },
    {
      "param_a": "A005",
      "param_b": "C030",
      "phenomenon": "极易分心且无法抑制冲动(ADHD型)",
      "value_a": 0.7320883674851029,
      "value_b": 0.9068398103913221
    },
    {
      "param_a": "A005",
      "param_b": "A008",
      "phenomenon": "高度集中但过度警觉(狙击手型)",
      "value_a": 0.7320883674851029,
      "value_b": 0.7128811485677105
    },
    {
      "param_a": "G064",
      "param_b": "B022",
      "phenomenon": "低相变阈值+高怨恨=一次背叛改变终身",
      "value_a": 0.8111581476576863,
      "value_b": 58.67287802921753
    },
    {
      "param_a": "E054",
      "param_b": "E048",
      "phenomenon": "高重构+高推脱=任何恶行都能被重新定义为善行",
      "value_a": 0.6137120036276709,
      "value_b": 0.662058733921236
    },
    {
      "param_a": "C027",
      "param_b": "C030",
      "phenomenon": "高折扣+低冲动控制=即时满足型",
      "value_a": 0.7997600990096976,
      "value_b": 0.9068398103913221
    },
    {
      "param_a": "C029",
      "param_b": "E045",
      "phenomenon": "永远不够好但对外声称很好(自恋-脆弱型)",
      "value_a": 0.6329503205343483,
      "value_b": 0.8583914184767831
    },
    {
      "param_a": "C029",
      "param_b": "E046",
      "phenomenon": "做了一点就觉得够了+精心展示=自我推销型",
      "value_a": 0.6329503205343483,
      "value_b": 0.6163450887931161
    },
    {
      "param_a": "E052",
      "param_b": "C026",
      "phenomenon": "高道德耦合+高意义寻求=在道德中寻找美/意义",
      "value_a": 0.707997930477946,
      "value_b": 15.066928641531703
    },
    {
      "param_a": "H073",
      "param_b": "F059",
      "phenomenon": "高抑制+高欺骗舒适=完美说谎者",
      "value_a": 0.6943474514306676,
      "value_b": 0.719120673941487
    },
    {
      "param_a": "C028",
      "param_b": "C031",
      "phenomenon": "高自主+高支配=我要主导但不要被主导",
      "value_a": 0.9481222336030792,
      "value_b": 0.6109655599154169
    },
    {
      "param_a": "A008",
      "param_b": "C030",
      "phenomenon": "高度警觉+冲动反应(先发制人型)",
      "value_a": 0.7128811485677105,
      "value_b": 0.9068398103913221
    }
  ],
  "collapse_table": [
    {
      "param_id": "B015",
      "param_name": "内疚感基线",
      "baseline": 0.5570959069355466,
      "by_relationship": {
        "家人": 0.7242246790162106,
        "竞争对手": 0.16712877208066396,
        "同事": 0.5013863162419919,
        "陌生人": 0.2785479534677733
      }
    },
    {
      "param_id": "A009",
      "param_name": "痛苦线索敏感度",
      "baseline": 0.19316373869311998,
      "by_relationship": {
        "竞争对手": 0.05794912160793599,
        "陌生人": 0.09658186934655999,
        "同事": 0.173847364823808,
        "家人": 0.251112860301056
      }
    },
    {
      "param_id": "C033",
      "param_name": "亲和动机",
      "baseline": 0.40808400860611793,
      "by_relationship": {
        "同事": 0.36727560774550616,
        "陌生人": 0.20404200430305897,
        "竞争对手": 0.12242520258183537,
        "家人": 0.5305092111879534
      }
    },
    {
      "param_id": "F061",
      "param_name": "信任默认值",
      "baseline": 0.016850382982900536,
      "by_relationship": {
        "陌生人": 0.008425191491450268,
        "竞争对手": 0.005055114894870161,
        "同事": 0.015165344684610482,
        "家人": 0.021905497877770696
      }
    },
    {
      "param_id": "D040",
      "param_name": "攻击行为基线",
      "baseline": 0.35028622394988185,
      "by_relationship": {
        "陌生人": 0.17514311197494092,
        "竞争对手": 0.10508586718496456,
        "同事": 0.3152576015548937,
        "家人": 0.4553720911348464
      }
    },
    {
      "param_id": "B021",
      "param_name": "情绪传染易感性",
      "baseline": 0.13680755397970223,
      "by_relationship": {
        "陌生人": 0.06840377698985112,
        "同事": 0.12312679858173202,
        "家人": 0.17784982017361292,
        "竞争对手": 0.041042266193910666
      }
    },
    {
      "param_id": "C031",
      "param_name": "支配-顺从倾向",
      "baseline": 0.6109655599154169,
      "by_relationship": {
        "陌生人": 0.30548277995770845,
        "竞争对手": 0.18328966797462506,
        "家人": 0.794255227890042,
        "同事": 0.5498690039238753
      }
    },
    {
      "param_id": "E046",
      "param_name": "外显自尊",
      "baseline": 0.6163450887931161,
      "by_relationship": {
        "陌生人": 0.30817254439655806,
        "竞争对手": 0.18490352663793483,
        "家人": 0.801248615431051,
        "同事": 0.5547105799138046
      }
    }
  ],
  "top_variances": [
    {
      "param_id": "G066",
      "variance": 324.3734754221863,
      "by_relationship": {
        "家人": 421.6855180488422,
        "竞争对手": 97.31204262665588,
        "同事": 291.93612787996767,
        "陌生人": 162.18673771109314
      }
    },
    {
      "param_id": "F056",
      "variance": 248.09738457399354,
      "by_relationship": {
        "家人": 322.5265999461916,
        "陌生人": 124.04869228699677,
        "竞争对手": 74.42921537219806,
        "同事": 223.28764611659417
      }
    },
    {
      "param_id": "D039",
      "variance": 110.54133635777455,
      "by_relationship": {
        "竞争对手": 33.16240090733236,
        "陌生人": 55.27066817888728,
        "家人": 143.70373726510692,
        "同事": 99.48720272199711
      }
    },
    {
      "param_id": "B022",
      "variance": 58.67287802921753,
      "by_relationship": {
        "家人": 76.27474143798278,
        "陌生人": 29.336439014608764,
        "竞争对手": 17.601863408765258,
        "同事": 52.80559022629578
      }
    },
    {
      "param_id": "C026",
      "variance": 15.066928641531705,
      "by_relationship": {
        "家人": 19.587007233991216,
        "竞争对手": 4.520078592459511,
        "同事": 13.560235777378534,
        "陌生人": 7.533464320765852
      }
    }
  ]
}